{
    "ne": [
        {
            "username": "bridge_allstar", 
            "tweet": "rt @mreese06: #patriots #patriots #patriots #patriots #patriots #patriots #patriots #patriots #patriots #patriots #patriots #patriots", 
            "fb_weight": 60
        }, 
        {
            "username": "bluedudesports", 
            "tweet": "bluedude sportstalk: #nfcwest #seahawks #49ers #rams #birdgang patriots put a 59 piece on the colts but gronk rep... http://t.co/5cdyr5sm", 
            "fb_weight": 21
        }, 
        {
            "username": "concussion962", 
            "tweet": "... fuck and double fuck. this #colts game is not going well... freaking patriots.... come on #colts! #chuckstrong #coltstrong", 
            "fb_weight": 18
        }, 
        {
            "username": "foreverunltd", 
            "tweet": "rt @espnstatsinfo: #patriots alfonzo dennard int return for td vs no. 1 pick, andrew luck. dennard was 224th overall pick in 2012 nfl draft", 
            "fb_weight": 18
        }, 
        {
            "username": "dak126", 
            "tweet": "rt @rochiewbz: andrew luck in 2012: 8 td - 2 int at home; 3 td - 9 int on the road. #wbz #patriots", 
            "fb_weight": 17
        }, 
        {
            "username": "serenatriano", 
            "tweet": "nfl fantasy football: rob gronkowski out 4-6 weeks: new england patriots tight end rob gronkowski is expect... http://t.co/tlwndr5k #nfl", 
            "fb_weight": 16
        }, 
        {
            "username": "xenafan2006", 
            "tweet": "rt @patriotsinsider: score: td pats (4thq 3:55) #patriots 59 - #colts 24 ... vereen 4-yd run  (drive: 7 plays, 39 yards in 3:42)", 
            "fb_weight": 16
        }, 
        {
            "username": "kdrummings", 
            "tweet": "rt @adwwwi: tom brady, aaron hernandez, & rob gronkowski \ud83d\ude0d\ud83d\udc99\u2764 #patriots", 
            "fb_weight": 16
        }, 
        {
            "username": "teerex_", 
            "tweet": "rt @turkeynoham: poly vs city , ravens vs steelers , tom brady vs payton manning , & woodlawn vs milford ! >>>>> best ...", 
            "fb_weight": 15
        }, 
        {
            "username": "trae_doby", 
            "tweet": "espn sc nfl - patriots te rob gronkowski suffered broken forearm in 4th qtr in sunday's win over colts - sources", 
            "fb_weight": 15
        }
    ]
}