{
    "gb": [
        {
            "username": "alliegatorrrr", 
            "tweet": "rt @em_fell_again: packers packers packers packers packers packers packers packers packers packers packers packers \ud83d\udc9a\ud83d\udc9b\ud83d\udc9a\ud83d\udc9b", 
            "fb_weight": 24
        }, 
        {
            "username": "beauty_no_beast", 
            "tweet": "rt @officialkingdre: cowboys, eagles, giants, redskins, patriots, colts, panthers, jets, packers, falcons, or steelers. #rt if you see y ...", 
            "fb_weight": 22
        }, 
        {
            "username": "iam_scrooge", 
            "tweet": "rt @officialkingdre: cowboys, eagles, giants, redskins, patriots, colts, panthers, jets, packers, falcons, or steelers. #rt if you see y ...", 
            "fb_weight": 22
        }, 
        {
            "username": "chelsey_leister", 
            "tweet": "rt @officialkingdre: cowboys, eagles, giants, redskins, patriots, colts, panthers, jets, packers, falcons, or steelers. #rt if you see y ...", 
            "fb_weight": 22
        }, 
        {
            "username": "merumuaddib", 
            "tweet": "rt @nflonfox: aaron rodgers spreads the wealth. randall cobb gets the 5 yard td grab. #packers lead the #rams 17-6.", 
            "fb_weight": 17
        }, 
        {
            "username": "a_adams88", 
            "tweet": "@daily_dip pats texans 49ers ravens vikings giants packers #dbh", 
            "fb_weight": 16
        }, 
        {
            "username": "dave_umbach", 
            "tweet": "rt @packernation: packers vs. rams: first half play by play http://t.co/ec5hpbj4 #packers #nfl", 
            "fb_weight": 14
        }, 
        {
            "username": "joe_polonia", 
            "tweet": "saints win, cowboys win, colts win, packers win, giants win, texans win, vikings win :)))", 
            "fb_weight": 14
        }, 
        {
            "username": "nursey_redleaf", 
            "tweet": "rt @packers: rams rb steven jackson runs in a td. packers 20, rams 13 with 8:50 left in the game. #gbvsstl", 
            "fb_weight": 14
        }, 
        {
            "username": "patrickclalonde", 
            "tweet": "aaron rodgers is one heck of a qb. league leading 18 touchdown passes. #packers #nfl", 
            "fb_weight": 13
        }
    ]
}